amaryllis/__init__.py
amaryllis/config.py
amaryllis/models/__init__.py
amaryllis/models/pension.py
amaryllis/models/single.py
amaryllis/survival_rate/population.py
amaryllis/util/__init__.py
amaryllis/util/calc_base.py
amaryllis/util/interest.py
models/__init__.py
models/pension.py
models/single.py
util/__init__.py
util/calc_base.py
util/interest.py
amaryllis-1.0.11.dist-info/METADATA
amaryllis-1.0.11.dist-info/WHEEL
amaryllis-1.0.11.dist-info/top_level.txt
amaryllis-1.0.11.dist-info/RECORD
