Metadata-Version: 2.1
Name: amaryllis
Version: 1.0.11
Summary: To calculate insurance value
Home-page: UNKNOWN
Author: yk-amary-20
Author-email: y.k.83600260@gmail.com
License: MIT
Keywords: amaryllis
Platform: UNKNOWN
Classifier: License :: OSI Approved :: MIT License
Classifier: Programming Language :: Python :: 3.6
Requires-Dist: numpy
